{
    "name": "Tanne",
    "dark": true,
    "author": "Emonadeo",
    "editorScheme": "/tanne.xml",
    "colors": {
        "conifer100": "#18201f",
        "conifer200": "#1b2423",
        "conifer300": "#232f2d",
        "conifer400": "#2b3b37",
        "conifer500": "#384D48",
        "conifer600": "#455e59",
        "conifer700": "#67837e",
        "conifer800": "#a8c7c0",
        "conifer900": "#dde5ed",
        "floralRed": "#f47653",
        "floralRedTransparent": "#f476530f",
        "floralOrange": "#ffc757",
        "floralOrangeTransparent": "#ffc7570f",
        "floralYellow": "#ffff57",
        "floralYellowTransparent": "#ffff570f",
        "floralGreen": "#a7e372",
        "floralGreenTransparent": "#a7e3720f",
        "floralBlue": "#79caf6",
        "floralBlueTransparent": "#79caf60f",
        "floralLilac": "#d488e7",
        "floralLilacTransparent": "#d488e70f"
    },
    "ui": {
        "*": {
            "acceleratorSelectionForeground": "conifer900",
            "background": "conifer200",
            "borderColor": "conifer400",
            "disabledBackground": "conifer100",
            "disabledForeground": "conifer600",
            "disabledText": "conifer600",
            "focusColor": "conifer600",
            "focusedBorderColor": "floralYellow",
            "foreground": "conifer900",
            "inactiveBackground": "conifer100",
            "inactiveForeground": "conifer800",
            "infoForeground": "conifer800",
            "selectionBackground": "conifer500",
            "selectionBackgroundInactive": "conifer500",
            "selectionForeground": "conifer900",
            "selectionInactiveBackground": "conifer500",
            "selectionInactiveForeground": "conifer900",
            "separatorColor": "conifer200"
        },
        "ActionButton": {
            "hoverBackground": "conifer300",
            "hoverBorderColor": "conifer400",
            "pressedBackground": "conifer300",
            "pressedBorderColor": "conifer400"
        },
        "Borders": {
            "ContrastBorderColor": "conifer400",
            "color": "conifer400"
        },
        "Button": {
            "arc": 4,
            "default": {
                "endBackground": "conifer300",
                "endBorderColor": "conifer400",
                "foreground": "conifer900",
                "focusColor": "floralYellow",
                "focusedBorderColor": "conifer400",
                "shadowColor": "conifer300",
                "startBackground": "conifer300",
                "startBorderColor": "conifer400"
            },
            "disabledBorderColor": "conifer400",
            "disabledText": "conifer600",
            "endBackground": "conifer300",
            "endBorderColor": "conifer400",
            "focusedBorderColor": "conifer400",
            "foreground": "conifer900",
            "shadowColor": "conifer300",
            "shadowWidth": 0,
            "startBackground": "conifer300",
            "startBorderColor": "conifer400"
        },
        "CheckBox": {
            "background": "conifer200",
            "disabledText": "conifer600",
            "foreground": "conifer900",
            "select": "floralYellow"
        },
        "CheckBoxMenuItem": {
            "acceleratorForeground": "conifer800",
            "acceleratorSelectionForeground": "conifer800",
            "background": "conifer200",
            "disabledBackground": "conifer200",
            "disabledForeground": "conifer600",
            "foreground": "conifer900",
            "selectionBackground": "conifer500",
            "selectionForeground": "floralYellow"
        },
        "ColorChooser": {
            "background": "conifer200",
            "foreground": "conifer900",
            "swatchesDefaultRecentColor": "conifer900"
        },
        "ComboBoxButton": {
            "background": "conifer300"
        },
        "ComboBox": {
            "ArrowButton": {
                "background": "conifer500",
                "disabledIconColor": "conifer600",
                "iconColor": "conifer900",
                "nonEditableBackground": "conifer200"
            },
            "background": "conifer300",
            "disabledForeground": "conifer600",
            "foreground": "conifer900",
            "modifiedItemForeground": "floralYellow",
            "nonEditableBackground": "conifer300",
            "selectionBackground": "conifer200",
            "selectionForeground": "floralYellow"
        },
        "ComboPopup": {
            "border": "conifer200"
        },
        "CompletionPopup": {
            "foreground": "conifer900",
            "matchForeground": "floralYellow",
            "selectionInactiveBackground": "conifer500",
            "selectionBackground": "conifer500"
        },
        "Component": {
            "arc": 4,
            "borderColor": "conifer400",
            "disabledBorderColor": "conifer400",
            "focusColor": "floralYellow",
            "focusedBorderColor": "floralYellow",
            "hoverIconColor": "floralYellow",
            "infoForeground": "conifer800",
            "iconColor": "conifer900"
        },
        "Counter": {
            "background": "floralYellow",
            "foreground": "conifer900"
        },
        "Debugger": {
            "Variables": {
                "collectingDataForeground": "conifer800",
                "changedValueForeground": "floralYellow",
                "errorMessageForeground": "#f47653",
                "evaluatingExpressionForeground": "conifer800",
                "exceptionForeground": "#5ad4e6",
                "modifyingValueForeground": "floralYellow",
                "valueForeground": "floralYellow"
            }
        },
        "DebuggerTabs": {
            "underlinedTabBackground": "conifer600"
        },
        "DebuggerPopup": {
            "borderColor": "conifer600"
        },
        "DefaultTabs": {
            "background": "conifer200",
            "borderColor": "conifer200",
            "hoverBackground": "conifer300",
            "inactiveUnderlineColor": "floralYellow",
            "underlineColor": "floralYellow",
            "underlinedTabBackground": "conifer200",
            "underlineHeight": 2
        },
        "DragAndDrop": {
            "areaBackground": "conifer200",
            "areaBorderColor": "conifer200",
            "areaForeground": "conifer900"
        },
        "Editor": {
            "background": "conifer200",
            "foreground": "conifer900",
            "shortcutForeground": "conifer800"
        },
        "EditorPane": {
            "background": "conifer200",
            "caretForeground": "floralYellow",
            "foreground": "conifer900",
            "inactiveBackground": "conifer200",
            "inactiveForeground": "conifer600",
            "selectionBackground": "conifer500",
            "selectionForeground": "floralYellow"
        },
        "EditorTabs": {
            "borderColor": "conifer400",
            "inactiveUnderlineColor": "floralYellow",
            "underlineColor": "floralYellow",
            "underlinedTabBackground": "conifer300",
            "underlinedTabForeground": "conifer900"
        },
        "FileColor": {
            "Blue":  "floralBlueTransparent",
            "Green": "floralGreenTransparent",
            "Orange": "floralOrangeTransparent",
            "Rose": "floralRedTransparent",
            "Violet": "floralLilacTransparent",
            "Yellow": "floralYellowTransparent"
        },
        "FormattedTextField": {
            "background": "conifer300",
            "caretForeground": "floralYellow",
            "foreground": "conifer900",
            "inactiveBackground": "conifer500",
            "inactiveForeground": "conifer600",
            "selectionForeground": "floralYellow",
            "selectionBackground": "conifer500"
        },
        "Group": {
            "disabledSeparatorColor": "conifer200",
            "separatorColor": "conifer200"
        },
        "GutterTooltip": {
            "infoForeground": "conifer900",
            "lineSeparatorColor": "conifer200"
        },
        "HelpTooltip": {
            "borderColor": "conifer200",
            "infoForeground": "conifer800"
        },
        "InformationHint": {
            "borderColor": "conifer200"
        },
        "InplaceRefactoringPopup": {
            "borderColor": "conifer200"
        },
        "Label": {
            "background": "conifer200",
            "disabledForeground": "conifer600",
            "disabledText": "conifer600",
            "foreground": "conifer800",
            "infoForeground": "conifer800",
            "selectedForeground": "floralYellow"
        },
        "Link": {
            "activeForeground": "floralYellow",
            "hoverForeground": "floralYellow",
            "pressedForeground": "floralYellow",
            "secondaryForeground": "conifer800",
            "visitedForeground": "floralYellow"
        },
        "List": {
            "background": "conifer200",
            "foreground": "conifer900",
            "selectionBackground": "conifer300",
            "selectionForeground": "floralYellow",
            "selectionInactiveBackground": "conifer300",
            "selectionInactiveForeground": "floralYellow"
        },
        "MemoryIndicator": {
            "allocatedBackground": "conifer500",
            "usedBackground": "conifer600"
        },
        "Menu": {
            "acceleratorForeground": "conifer800",
            "acceleratorSelectionForeground": "conifer900",
            "background": "conifer200",
            "borderColor": "conifer400",
            "disabledBackground": "conifer500",
            "disabledForeground": "conifer600",
            "foreground": "conifer900",
            "separatorColor": "conifer200",
            "selectionForeground": "floralYellow"
        },
        "MenuBar": {
            "borderColor": "conifer200",
            "disabledBackground": "conifer200",
            "disabledForeground": "conifer600",
            "foreground": "conifer900",
            "highlight": "conifer200",
            "selectionBackground": "conifer500",
            "selectionForeground": "floralYellow",
            "shadow": "conifer100"
        },
        "MenuItem": {
            "acceleratorForeground": "conifer800",
            "background": "conifer200",
            "disabledBackground": "conifer200",
            "disabledForeground": "conifer600",
            "foreground": "conifer900",
            "selectionBackground": "conifer500",
            "selectionForeground": "floralYellow"
        },
        "NavBar": {
            "borderColor": "conifer400"
        },
        "Notification": {
            "background": "conifer300",
            "borderColor": "conifer100",
            "errorBackground": "conifer100",
            "errorBorderColor": "conifer100",
            "foreground": "conifer900",
            "MoreButton": {
                "background": "conifer500",
                "foreground": "conifer900",
                "innerBorderColor": "conifer400"
            },
            "ToolWindow": {
                "errorBackground": "conifer300",
                "errorBorderColor": "conifer400",
                "informativeBackground": "conifer300",
                "informativeBorderColor": "conifer400",
                "warningBackground": "conifer300",
                "warningBorderColor": "conifer400"
            }
        },
        "OptionPane": {
            "background": "conifer200",
            "foreground": "conifer900",
            "messageForeground": "conifer900"
        },
        "Panel": {
            "background": "conifer200",
            "foreground": "conifer800"
        },
        "ParameterInfo": {
            "background": "conifer500",
            "borderColor": "conifer400",
            "currentOverloadBackground": "conifer500",
            "currentParameterForeground": "floralYellow",
            "disabledForeground": "conifer600",
            "foreground": "conifer900",
            "infoForeground": "conifer800",
            "lineSeparatorColor": "conifer400"
        },
        "PasswordField": {
            "background": "conifer500",
            "capsLockIconColor": "floralYellow",
            "caretForeground": "floralYellow",
            "foreground": "conifer900",
            "inactiveForeground": "conifer600",
            "selectionBackground": "conifer600",
            "selectionForeground": "floralYellow"
        },
        "Plugins": {
            "background": "conifer200",
            "disabledForeground": "conifer800",
            "eapTagBackground": "conifer600",
            "lightSelectionBackground": "conifer300",
            "hoverBackground": "conifer300",
            "tagForeground": "floralYellow",
            "tagBackground": "#242C2C",
            "Button": {
                "installBackground": "conifer100",
                "installBorderColor": "conifer100",
                "installForeground": "conifer900",
                "installFocusedBackground": "conifer100",
                "installFillForeground": "conifer800",
                "installFillBackground": "conifer100",
                "updateBackground": "conifer100",
                "updateBorderColor": "conifer100",
                "updateForeground": "conifer900"
            },
            "SearchField": {
                "background": "conifer300",
                "borderColor": "conifer400"
            },
            "SectionHeader": {
                "background": "conifer200",
                "foreground": "conifer800"
            },
            "Tab": {
                "hoverBackground": "conifer300",
                "selectedForeground": "conifer900",
                "selectedBackground": "conifer300"
            }
        },
        "Popup": {
            "Advertiser": {
                "background": "conifer200",
                "borderColor": "conifer200",
                "foreground": "floralYellow"
            },
            "borderColor": "conifer100",
            "inactiveBorderColor": "conifer200",
            "innerBorderColor": "conifer200",
            "Header": {
                "activeBackground": "conifer200",
                "inactiveBackground": "conifer100"
            },
            "paintBorder": true,
            "separatorForeground": "conifer900",
            "separatorColor": "conifer200",
            "Toolbar": {
                "background": "conifer100",
                "borderColor": "conifer400"
            }
        },
        "PopupMenu": {
            "background": "conifer200",
            "foreground": "conifer900",
            "translucentBackground": "conifer200",
            "selectionBackground": "conifer500"
        },
        "PopupMenuSeparator": {
            "height": 10,
            "stripeIndent": 5
        },
        "ProgressBar": {
            "background": "conifer200",
            "foreground": "floralYellow",
            "indeterminateEndColor": "floralYellow",
            "indeterminateStartColor": "floralYellow",
            "progressColor": "floralYellow",
            "selectionBackground": "conifer600",
            "trackColor": "conifer600"
        },
        "RadioButton": {
            "background": "conifer200",
            "disabledText": "conifer600",
            "foreground": "conifer900"
        },
        "RadioButtonMenuItem": {
            "acceleratorForeground": "conifer800",
            "acceleratorSelectionForeground": "conifer800",
            "background": "conifer200",
            "disabledBackground": "conifer200",
            "disabledForeground": "conifer600",
            "foreground": "conifer900",
            "selectionBackground": "conifer500",
            "selectionForeground": "floralYellow"
        },
        "ScrollBar":  {
            "trackColor": "conifer200",
            "thumbColor": "conifer500",
            "thumbBorderColor": "conifer500",
            "hoverTrackColor": "conifer200",
            "hoverThumbColor": "conifer700",
            "hoverThumbBorderColor": "conifer700",
            "Transparent": {
                "trackColor": "conifer200",
                "thumbColor": "conifer500",
                "thumbBorderColor": "conifer500",
                "hoverTrackColor": "conifer200",
                "hoverThumbColor": "conifer700",
                "hoverThumbBorderColor": "conifer700"
            },
            "Mac": {
                "trackColor": "conifer200",
                "thumbColor": "conifer500",
                "thumbBorderColor": "conifer500",
                "hoverTrackColor": "conifer200",
                "hoverThumbColor": "conifer700",
                "hoverThumbBorderColor": "conifer700",
                "Transparent": {
                    "trackColor": "conifer200",
                    "thumbColor": "conifer500",
                    "thumbBorderColor": "conifer500",
                    "hoverTrackColor": "conifer200",
                    "hoverThumbColor": "conifer700",
                    "hoverThumbBorderColor": "conifer700"
                }
            }
        },
        "SearchEverywhere": {
            "Advertiser": {
                "background": "conifer100",
                "foreground": "conifer800"
            },
            "Header": {
                "background": "conifer200"
            },
            "List": {
                "separatorColor": "conifer200",
                "separatorForeground": "conifer800"
            },
            "SearchField": {
                "background": "conifer200",
                "borderColor": "conifer100",
                "infoForeground": "conifer800"
            },
            "Tab": {
                "selectedForeground": "floralYellow",
                "selectedBackground": "conifer600"
            }
        },
        "SearchMatch": {
            "endBackground": "floralYellow",
            "startBackground": "floralYellow"
        },
        "Separator": {
            "separatorColor": "conifer300"
        },
        "SidePanel": {
            "background": "conifer200"
        },
        "Slider": {
            "background": "conifer200",
            "buttonBorderColor": "floralYellow",
            "buttonColor": "floralYellow",
            "foreground": "conifer900",
            "tickColor": "conifer500",
            "trackColor": "conifer500"
        },
        "SpeedSearch": {
            "background": "conifer600",
            "borderColor": "conifer200",
            "errorForeground": "conifer900",
            "foreground": "conifer900"
        },
        "Spinner": {
            "background": "conifer200"
        },
        "SplitPane": {
            "background": "conifer200",
            "highlight": "conifer100"
        },
        "SplitPaneDivider": {
            "draggingColor": "conifer500"
        },
        "StatusBar": {
            "borderColor": "conifer400",
            "hoverBackground": "conifer300"
        },
        "TabbedPane": {
            "background": "conifer200",
            "contentAreaColor": "conifer600",
            "disabledForeground": "conifer600",
            "disabledUnderlineColor": "conifer600",
            "focus": "conifer500",
            "focusColor": "conifer500",
            "foreground": "conifer900",
            "hoverColor": "conifer300",
            "tabSelectionHeight": 2,
            "underlineColor": "floralYellow"
        },
        "Table": {
            "background": "conifer200",
            "dropLineColor": "floralYellow",
            "dropLineShortColor": "floralYellow",
            "focusCellBackground": "conifer100",
            "focusCellForeground": "floralYellow",
            "foreground": "conifer900",
            "gridColor": "conifer100",
            "lightSelectionForeground": "floralYellow",
            "lightSelectionInactiveForeground": "conifer900",
            "lightSelectionInactiveBackground": "conifer300",
            "selectionBackground": "conifer300",
            "selectionForeground": "floralYellow",
            "selectionInactiveBackground": "conifer300",
            "selectionInactiveForeground": "conifer900",
            "sortIconColor": "conifer900",
            "stripeColor": "conifer100"
        },
        "TableHeader": {
            "background": "conifer200",
            "bottomSeparatorColor": "conifer300",
            "cellBorder": "4,0,4,0",
            "foreground": "conifer900",
            "focusCellBackground": "conifer500",
            "separatorColor": "conifer300"
        },
        "textText": "conifer800",
        "TextArea": {
            "background": "conifer300",
            "caretForeground": "floralYellow",
            "foreground": "conifer900",
            "inactiveForeground": "conifer600",
            "selectionBackground": "conifer600",
            "selectionForeground": "floralYellow"
        },
        "TextField": {
            "background": "conifer300",
            "caretForeground": "floralYellow",
            "foreground": "conifer900",
            "inactiveForeground": "conifer600",
            "selectionBackground": "conifer600",
            "selectionForeground": "floralYellow"
        },
        "TextPane": {
            "background": "conifer300",
            "caretForeground": "floralYellow",
            "foreground": "conifer900",
            "inactiveForeground": "conifer600",
            "selectionBackground": "conifer600",
            "selectionForeground": "floralYellow"
        },
        "TitlePane": {
            "inactiveBackground": "conifer200",
            "infoForeground": "conifer800",
            "inactiveInfoForeground": "conifer800"
        },
        "TitledBorder": {
            "titleColor": "conifer200"
        },
        "ToggleButton": {
            "borderColor": "conifer500",
            "buttonColor": "conifer900",
            "disabledText": "conifer600",
            "foreground": "conifer800",
            "offForeground": "conifer200",
            "offBackground": "conifer200",
            "onBackground": "floralYellow",
            "onForeground": "floralYellow"
        },
        "ToolBar": {
            "background": "#222222",
            "borderHandleColor": "conifer800",
            "floatingForeground": "conifer800",
            "foreground": "conifer900"
        },
        "ToolTip": {
            "Actions": {
                "background": "conifer200",
                "infoForeground": "conifer800"
            },
            "background": "conifer200",
            "borderColor": "conifer600",
            "foreground": "conifer900",
            "infoForeground": "conifer800",
            "shortcutForeground": "conifer800"
        },
        "ToolWindow": {
            "Button": {
                "hoverBackground": "conifer300",
                "selectedForeground": "floralYellow",
                "selectedBackground": "conifer300"
            },
            "Header": {
                "background": "conifer200",
                "borderColor": "conifer400",
                "inactiveBackground": "conifer200"
            },
            "HeaderCloseButton": {
                "background": "conifer200"
            },
            "HeaderTab": {
                "hoverBackground": "conifer300",
                "hoverInactiveBackground": "conifer300",
                "inactiveUnderlineColor": "floralYellow",
                "selectedInactiveBackground": "conifer200",
                "underlineColor": "floralYellow",
                "underlinedTabBackground": "conifer300",
                "underlinedTabInactiveBackground": "conifer300"
            }
        },
        "Tree": {
            "background": "conifer200",
            "foreground": "conifer900",
            "hash": "conifer200",
            "modifiedItemForeground": "conifer900",
            "rowHeight": 27,
            "selectionBackground": "conifer300",
            "selectionForeground": "conifer900",
            "selectionInactiveBackground": "conifer200"
        },
        "UiDesigner": {
            "Panel": {
                "background": "conifer200"
            },
            "Preview": {
                "background": "conifer200"
            }
        },
        "ValidationTooltip": {
            "errorBackground": "conifer300",
            "errorBorderColor": "conifer400",
            "warningBackground": "conifer300",
            "warningBorderColor": "conifer400"
        },
        "VersionControl": {
            "FileHistory": {
                "Commit": {
                    "selectedBranchBackground": "conifer200"
                }
            },
            "GitLog": {
                "localBranchIconColor": "floralYellow",
                "otherIconColor": "conifer800",
                "remoteBranchIconColor": "conifer900",
                "tagIconColor": "conifer800"
            },
            "HgLog": {
                "branchIconColor": "floralYellow",
                "bookmarkIconColor": "floralYellow",
                "closedBranchIconColor": "conifer600",
                "localTagIconColor": "conifer800",
                "mqTagIconColor": "conifer800",
                "tagIconColor": "conifer800",
                "tipIconColor": "conifer800"
            },
            "Log": {
                "Commit": {
                    "unmatchedForeground": "conifer800",
                    "currentBranchBackground": "conifer300"
                }
            },
            "RefLabel": {
                "foreground": "floralYellow",
                "backgroundBase": "conifer600"
            }
        },
        "Viewport": {
            "background": "conifer100",
            "foreground": "conifer900"
        },
        "WelcomeScreen": {
            "background": "conifer200",
            "borderColor": "conifer400",
            "captionBackground": "conifer100",
            "captionForeground": "conifer900",
            "footerBackground": "conifer100",
            "footerForeground": "conifer900",
            "headerBackground": "conifer200",
            "headerForeground": "conifer900",
            "Projects": {
                "background": "conifer100",
                "selectionBackground": "conifer200",
                "selectionInactiveBackground": "conifer200"
            },
            "separatorColor": "conifer300"
        },
        "window": "conifer200",
        "Window": {
            "border": "0,0,0,0,conifer400"
        },
        "windowBorder": "conifer400",
        "windowText": "conifer800"
    },
    "icons": {
        "ColorPalette": {
            "Checkbox.Background.Default.Dark": "conifer500",
            "Checkbox.Background.Disabled.Dark": "conifer100",
            "Checkbox.Background.Selected.Dark": "conifer500",
            "Checkbox.Border.Default.Dark": "conifer500",
            "Checkbox.Border.Disabled.Dark": "conifer100",
            "Checkbox.Border.Selected.Dark": "conifer500",
            "Checkbox.Focus.Thin.Default.Dark": "conifer500",
            "Checkbox.Focus.Thin.Selected.Dark": "conifer100",
            "Checkbox.Focus.Wide.Dark": "conifer500",
            "Checkbox.Foreground.Disabled.Dark": "conifer800",
            "Checkbox.Foreground.Selected.Dark": "conifer900"
        }
    }
}
